LICENSE
MANIFEST.in
README.HTML
README.md
setup.cfg
setup.py
waihonanumpy/Storage.py
waihonanumpy/__init__.py
waihonanumpy.egg-info/PKG-INFO
waihonanumpy.egg-info/SOURCES.txt
waihonanumpy.egg-info/dependency_links.txt
waihonanumpy.egg-info/requires.txt
waihonanumpy.egg-info/top_level.txt