Metadata-Version: 2.1
Name: waihonanumpy
Version: 0.0.4.4
Summary: Store and retreive data in Redis.
Home-page: https://github.com/radiomicsvhio/waihona-numpy
Author: Camilo A. Monreal
Author-email: camilomonreal@vhio.net
License: cc-by-sa-4.0
Download-URL: https://github.com/radiomicsvhio/waihona-numpy/releases/download/v0.0.1/waihonanumpy-v0.0.1.tar.gz
Keywords: redis,numpy,store
Platform: UNKNOWN
Classifier: Development Status :: 3 - Alpha
Classifier: Intended Audience :: Developers
Classifier: Topic :: Software Development :: Build Tools
Classifier: License :: OSI Approved :: MIT License
Classifier: Programming Language :: Python :: 3
Classifier: Programming Language :: Python :: 3.4
Classifier: Programming Language :: Python :: 3.5
Classifier: Programming Language :: Python :: 3.6
Classifier: Programming Language :: Python :: 3.7
Classifier: Programming Language :: Python :: 3.8
Classifier: Programming Language :: Python :: 3.9
License-File: LICENSE
